{
  "title": "顾客好评",
  "subTitle":"重振雄风，给你前所未有的能力",
  "commentList" : [
    {
      "avatarSrc": "static/img/a1.jpg",
      "location": "江苏",
      "name" : "李先生",
      "star" : 4,
      "time"     : "2017-04-24 15:12",
      "content" :"今年24岁，刚参加工作手里也没有多少钱，和女朋友分手也都是因为时间短，先买了一个周期的， 用完以后时间能有35分钟左右，现在正在使用第二个周期，很期待增长3厘米 好评！"
    },
    {
      "avatarSrc": "static/img/a2.jpg",
      "location": "湖南",
      "name" : "王女士",
      "star" : 3,
      "time"     : "2017-04-24 15:12",
      "content" :"今年24岁，刚参加工作手里也没有多少钱，和女朋友分手也都是因为时间短， 用完以后时间能有35分钟左右，现在正在使用第二个周期，很期待增长3厘米 好评！"
    },
    {
      "avatarSrc": "static/img/a3.jpg",
      "location": "山西",
      "name" : "赵先生",
      "star" : 5,
      "time"     : "2017-04-24 15:12",
      "content" :"今年24岁，刚参加工作手里也没有多少钱，，先买了一个周期的， 用完以后时间能有35分钟左右，现在正在使用第二个周期，很期待增长3厘米 好评！"
    },
    {
      "avatarSrc": "static/img/a4.jpg",
      "location": "北京",
      "name" : "李总",
      "star" : 3,
      "time"     : "2017-04-24 15:12",
      "content" :"今年24岁，刚参加工作手里也没有多少钱，和女朋友分手也都是因为时间短，先买了一个周期的， 用完以后时间能有35分钟左右，现在正在使用第二个周期，很期待增长3厘米 好评！"
    },
    {
      "avatarSrc": "static/img/a5.jpg",
      "location": "广西",
      "name" : "李先生",
      "star" : 5,
      "time"     : "2017-04-24 15:12",
      "content" :"今年24岁，刚参加工作手里也没有多少钱，和女朋友分手也都是因为时间短，先买了一个周期的， 用完以后时间能有35分钟左右，很期待增长3厘米 好评！"
    }
  ],
  "pic1": "static/img/man3.png"

}
